LICENSE
README.md
setup.py
examples/__init__.py
examples/demo-financials.py
examples/demo-tables.py
graham/__init__.py
graham/equities.py
graham/tables.py
graham_client.egg-info/PKG-INFO
graham_client.egg-info/SOURCES.txt
graham_client.egg-info/dependency_links.txt
graham_client.egg-info/requires.txt
graham_client.egg-info/top_level.txt