Metadata-Version: 2.1
Name: graham-client
Version: 0.0.4
Summary: A Python client for withgraham.io
Author: WithGraham
Author-email: support@withgraham.io
Keywords: python,financial,data,api,withgraham,graham,value investing
License-File: LICENSE
